appdata_logger/__init__.py
appdata_logger-0.2.2.dist-info/LICENSE
appdata_logger-0.2.2.dist-info/METADATA
appdata_logger-0.2.2.dist-info/WHEEL
appdata_logger-0.2.2.dist-info/top_level.txt
appdata_logger-0.2.2.dist-info/RECORD
