Metadata-Version: 2.2
Name: appdata-logger
Version: 0.2.2
Summary: Configure logger to write logs into the appdata directory
Author-email: Alexander Ivanov <alexander.vl.ivanov@gmail.com>
Project-URL: Homepage, https://github.com/a-iv/appdata-logger
Project-URL: Issues, https://github.com/a-iv/appdata-logger/issues
Classifier: Programming Language :: Python :: 3
Classifier: License :: OSI Approved :: MIT License
Classifier: Operating System :: Microsoft :: Windows
Requires-Python: >=3.6
License-File: LICENSE
